[
  {
    "key": "user:1:bio",
    "value": "Software engineer interested in databases and Go",
    "is_binary": false
  },
  {
    "key": "user:2:name",
    "value": "Bob Smith",
    "is_binary": false
  },
  {
    "key": "user:2:email",
    "value": "bob@example.com",
    "is_binary": false
  },
  {
    "key": "binary:data",
    "value_b64": "AAECA//+/Q==",
    "is_binary": true
  },
  {
    "key": "config:theme",
    "value": "dark",
    "is_binary": false
  },
  {
    "key": "config:lang",
    "value": "en",
    "is_binary": false
  },
  {
    "key": "user:1:name",
    "value": "Alice Johnson",
    "is_binary": false
  },
  {
    "key": "user:1:email",
    "value": "alice@example.com",
    "is_binary": false
  }
]
